{
  "patient": {
    "row_count": 352161,
    "columns": [
      "Patient_ID",
      "Sex",
      "BirthYear",
      "BirthMonth",
      "OptedOut",
      "OptOutDate",
      "Sex_normalized",
      "Age"
    ],
    "dtypes": {
      "Patient_ID": "int64",
      "Sex": "object",
      "BirthYear": "float64",
      "BirthMonth": "float64",
      "OptedOut": "bool",
      "OptOutDate": "float64",
      "Sex_normalized": "object",
      "Age": "float64"
    }
  },
  "patient_demographic": {
    "row_count": 352220,
    "columns": [
      "PatientDemographic_ID",
      "Network_ID",
      "Site_ID",
      "Patient_ID",
      "Cycle_ID",
      "Occupation",
      "HighestEducation",
      "HousingStatus",
      "ResidencePostalCode",
      "PatientStatus_orig",
      "PatientStatus_calc",
      "Language",
      "Ethnicity",
      "DeceasedYear",
      "DateCreated",
      "Sex",
      "BirthYear",
      "BirthMonth",
      "OptedOut",
      "OptOutDate",
      "recorded_deceased",
      "age"
    ],
    "dtypes": {
      "PatientDemographic_ID": "int64",
      "Network_ID": "int64",
      "Site_ID": "int64",
      "Patient_ID": "int64",
      "Cycle_ID": "object",
      "Occupation": "object",
      "HighestEducation": "object",
      "HousingStatus": "object",
      "ResidencePostalCode": "float64",
      "PatientStatus_orig": "object",
      "PatientStatus_calc": "object",
      "Language": "object",
      "Ethnicity": "object",
      "DeceasedYear": "float64",
      "DateCreated": "object",
      "Sex": "object",
      "BirthYear": "float64",
      "BirthMonth": "float64",
      "OptedOut": "bool",
      "OptOutDate": "float64",
      "recorded_deceased": "object",
      "age": "float64"
    }
  },
  "encounter": {
    "row_count": 11577739,
    "columns": [
      "Encounter_ID",
      "Network_ID",
      "Site_ID",
      "Patient_ID",
      "Provider_ID",
      "Cycle_ID",
      "EncounterDate",
      "Reason_orig",
      "Reason_calc",
      "EncounterType",
      "DateCreated"
    ],
    "dtypes": {
      "Encounter_ID": "int64",
      "Network_ID": "int64",
      "Site_ID": "int64",
      "Patient_ID": "int64",
      "Provider_ID": "int64",
      "Cycle_ID": "object",
      "EncounterDate": "datetime64[ns]",
      "Reason_orig": "object",
      "Reason_calc": "float64",
      "EncounterType": "object",
      "DateCreated": "datetime64[ns]"
    }
  },
  "encounter_diagnosis": {
    "row_count": 12471764,
    "columns": [
      "EncounterDiagnosis_ID",
      "Network_ID",
      "Site_ID",
      "Patient_ID",
      "Encounter_ID",
      "Cycle_ID",
      "DiagnosisText_orig",
      "DiagnosisText_calc",
      "DiagnosisCodeType_orig",
      "DiagnosisCodeType_calc",
      "DiagnosisCode_orig",
      "DiagnosisCode_calc",
      "DateCreated",
      "orphan_encounter",
      "code_root"
    ],
    "dtypes": {
      "EncounterDiagnosis_ID": "int64",
      "Network_ID": "int64",
      "Site_ID": "int64",
      "Patient_ID": "int64",
      "Encounter_ID": "float64",
      "Cycle_ID": "object",
      "DiagnosisText_orig": "object",
      "DiagnosisText_calc": "object",
      "DiagnosisCodeType_orig": "object",
      "DiagnosisCodeType_calc": "object",
      "DiagnosisCode_orig": "object",
      "DiagnosisCode_calc": "object",
      "DateCreated": "datetime64[ns]",
      "orphan_encounter": "bool",
      "code_root": "object"
    }
  },
  "health_condition": {
    "row_count": 2571583,
    "columns": [
      "HealthCondition_ID",
      "Network_ID",
      "Site_ID",
      "Patient_ID",
      "Encounter_ID",
      "Cycle_ID",
      "DiagnosisText_orig",
      "DiagnosisText_calc",
      "DiagnosisCodeType_orig",
      "DiagnosisCodeType_calc",
      "DiagnosisCode_orig",
      "DiagnosisCode_calc",
      "DateOfOnset",
      "SignificantNegativeFlag",
      "ActiveInactiveFlag",
      "DateCreated"
    ],
    "dtypes": {
      "HealthCondition_ID": "int64",
      "Network_ID": "int64",
      "Site_ID": "int64",
      "Patient_ID": "int64",
      "Encounter_ID": "float64",
      "Cycle_ID": "object",
      "DiagnosisText_orig": "object",
      "DiagnosisText_calc": "object",
      "DiagnosisCodeType_orig": "object",
      "DiagnosisCodeType_calc": "object",
      "DiagnosisCode_orig": "object",
      "DiagnosisCode_calc": "object",
      "DateOfOnset": "datetime64[ns]",
      "SignificantNegativeFlag": "bool",
      "ActiveInactiveFlag": "object",
      "DateCreated": "datetime64[ns]"
    }
  },
  "lab": {
    "row_count": 0,
    "columns": [
      "Lab_ID",
      "Network_ID",
      "Site_ID",
      "Patient_ID",
      "Encounter_ID",
      "Cycle_ID",
      "PerformedDate",
      "Name_orig",
      "Name_calc",
      "CodeType_orig",
      "CodeType_calc",
      "Code_orig",
      "Code_calc",
      "TestResult_orig",
      "TestResult_calc",
      "UpperNormal",
      "LowerNormal",
      "NormalRange",
      "UnitOfMeasure_orig",
      "UnitOfMeasure_calc",
      "DateCreated",
      "orphan_encounter",
      "Linked_Encounter_ID",
      "Days_To_Encounter",
      "Linkage_Confidence",
      "Effective_Encounter_ID",
      "is_normal",
      "result_numeric",
      "TestResult_numeric",
      "upper_numeric",
      "lower_numeric"
    ],
    "dtypes": {
      "Lab_ID": "int64",
      "Network_ID": "int64",
      "Site_ID": "int64",
      "Patient_ID": "int64",
      "Encounter_ID": "float64",
      "Cycle_ID": "object",
      "PerformedDate": "object",
      "Name_orig": "object",
      "Name_calc": "object",
      "CodeType_orig": "float64",
      "CodeType_calc": "object",
      "Code_orig": "float64",
      "Code_calc": "object",
      "TestResult_orig": "object",
      "TestResult_calc": "float64",
      "UpperNormal": "float64",
      "LowerNormal": "object",
      "NormalRange": "object",
      "UnitOfMeasure_orig": "object",
      "UnitOfMeasure_calc": "object",
      "DateCreated": "object",
      "orphan_encounter": "bool",
      "Linked_Encounter_ID": "float64",
      "Days_To_Encounter": "float64",
      "Linkage_Confidence": "float64",
      "Effective_Encounter_ID": "float64",
      "is_normal": "object",
      "result_numeric": "float64",
      "TestResult_numeric": "float64",
      "upper_numeric": "float64",
      "lower_numeric": "float64"
    }
  },
  "medication": {
    "row_count": 7706628,
    "columns": [
      "Medication_ID",
      "Network_ID",
      "Site_ID",
      "Patient_ID",
      "Encounter_ID",
      "Cycle_ID",
      "StartDate",
      "StopDate",
      "Reason",
      "DIN",
      "Name_orig",
      "Name_calc",
      "CodeType_orig",
      "CodeType_calc",
      "Code_orig",
      "Code_calc",
      "Strength",
      "Dose",
      "UnitOfMeasure",
      "Frequency",
      "DurationCount",
      "DurationUnit",
      "DispensedCount",
      "DispensedForm",
      "RefillCount",
      "DateCreated",
      "orphan_encounter"
    ],
    "dtypes": {
      "Medication_ID": "int64",
      "Network_ID": "int64",
      "Site_ID": "int64",
      "Patient_ID": "int64",
      "Encounter_ID": "float64",
      "Cycle_ID": "object",
      "StartDate": "datetime64[ns]",
      "StopDate": "datetime64[ns]",
      "Reason": "object",
      "DIN": "object",
      "Name_orig": "object",
      "Name_calc": "object",
      "CodeType_orig": "object",
      "CodeType_calc": "object",
      "Code_orig": "object",
      "Code_calc": "object",
      "Strength": "object",
      "Dose": "object",
      "UnitOfMeasure": "object",
      "Frequency": "object",
      "DurationCount": "float64",
      "DurationUnit": "object",
      "DispensedCount": "float64",
      "DispensedForm": "object",
      "RefillCount": "float64",
      "DateCreated": "datetime64[ns]",
      "orphan_encounter": "bool"
    }
  },
  "referral": {
    "row_count": 1141061,
    "columns": [
      "Referral_ID",
      "Network_ID",
      "Site_ID",
      "Patient_ID",
      "Encounter_ID",
      "Cycle_ID",
      "CompletedDate",
      "Name_orig",
      "Name_calc",
      "ConceptCode",
      "DescriptionCode",
      "DateCreated",
      "EffectiveDate",
      "DateSource",
      "ReferralStatus",
      "to_psychiatrist",
      "to_cardio",
      "to_gastro",
      "to_neuro",
      "to_musculo",
      "to_respiratory",
      "to_endo",
      "to_derm",
      "to_gyn",
      "to_any_body_system"
    ],
    "dtypes": {
      "Referral_ID": "int64",
      "Network_ID": "int64",
      "Site_ID": "int64",
      "Patient_ID": "int64",
      "Encounter_ID": "float64",
      "Cycle_ID": "object",
      "CompletedDate": "datetime64[ns]",
      "Name_orig": "object",
      "Name_calc": "object",
      "ConceptCode": "float64",
      "DescriptionCode": "object",
      "DateCreated": "datetime64[ns]",
      "EffectiveDate": "datetime64[ns]",
      "DateSource": "object",
      "ReferralStatus": "object",
      "to_psychiatrist": "bool",
      "to_cardio": "bool",
      "to_gastro": "bool",
      "to_neuro": "bool",
      "to_musculo": "bool",
      "to_respiratory": "bool",
      "to_endo": "bool",
      "to_derm": "bool",
      "to_gyn": "bool",
      "to_any_body_system": "bool"
    }
  },
  "family_history": {
    "row_count": 325202,
    "columns": [
      "FamilyHistory_ID",
      "Network_ID",
      "Site_ID",
      "Patient_ID",
      "Encounter_ID",
      "Cycle_ID",
      "DiagnosisText_orig",
      "DiagnosisText_calc",
      "DiagnosisCodeType_orig",
      "DiagnosisCodeType_calc",
      "DiagnosisCode_orig",
      "DiagnosisCode_calc",
      "Relationship_orig",
      "Relationship_Side_calc",
      "Relationship_Degree_calc",
      "AgeAtOnset",
      "VitalStatus",
      "WasCauseOfDeath",
      "AgeAtDeath",
      "DateCreated"
    ],
    "dtypes": {
      "FamilyHistory_ID": "int64",
      "Network_ID": "int64",
      "Site_ID": "int64",
      "Patient_ID": "int64",
      "Encounter_ID": "float64",
      "Cycle_ID": "object",
      "DiagnosisText_orig": "object",
      "DiagnosisText_calc": "float64",
      "DiagnosisCodeType_orig": "object",
      "DiagnosisCodeType_calc": "float64",
      "DiagnosisCode_orig": "object",
      "DiagnosisCode_calc": "float64",
      "Relationship_orig": "object",
      "Relationship_Side_calc": "float64",
      "Relationship_Degree_calc": "float64",
      "AgeAtOnset": "float64",
      "VitalStatus": "object",
      "WasCauseOfDeath": "bool",
      "AgeAtDeath": "float64",
      "DateCreated": "object"
    }
  },
  "medical_procedure": {
    "row_count": 1203002,
    "columns": [
      "MedicalProcedure_ID",
      "Network_ID",
      "Site_ID",
      "Patient_ID",
      "Encounter_ID",
      "Cycle_ID",
      "PerformedDate",
      "Name_orig",
      "Name_calc",
      "DateCreated"
    ],
    "dtypes": {
      "MedicalProcedure_ID": "int64",
      "Network_ID": "int64",
      "Site_ID": "int64",
      "Patient_ID": "int64",
      "Encounter_ID": "float64",
      "Cycle_ID": "object",
      "PerformedDate": "datetime64[ns]",
      "Name_orig": "object",
      "Name_calc": "float64",
      "DateCreated": "datetime64[ns]"
    }
  },
  "risk_factor": {
    "row_count": 603298,
    "columns": [
      "RiskFactor_ID",
      "Network_ID",
      "Site_ID",
      "Patient_ID",
      "Encounter_ID",
      "Cycle_ID",
      "StartDate",
      "EndDate",
      "Name_orig",
      "Name_calc",
      "Value_orig",
      "Value_calc",
      "Status_orig",
      "Status_calc",
      "Frequency",
      "FrequencyType",
      "FrequencyUnit",
      "Duration",
      "DurationType",
      "DurationUnit",
      "EndDuration",
      "EndDurationType",
      "EndDurationUnit",
      "RiskDetails",
      "DateCreated"
    ],
    "dtypes": {
      "RiskFactor_ID": "int64",
      "Network_ID": "int64",
      "Site_ID": "int64",
      "Patient_ID": "int64",
      "Encounter_ID": "float64",
      "Cycle_ID": "object",
      "StartDate": "datetime64[ns]",
      "EndDate": "datetime64[ns]",
      "Name_orig": "object",
      "Name_calc": "object",
      "Value_orig": "object",
      "Value_calc": "object",
      "Status_orig": "object",
      "Status_calc": "float64",
      "Frequency": "float64",
      "FrequencyType": "float64",
      "FrequencyUnit": "object",
      "Duration": "float64",
      "DurationType": "float64",
      "DurationUnit": "float64",
      "EndDuration": "float64",
      "EndDurationType": "float64",
      "EndDurationUnit": "float64",
      "RiskDetails": "object",
      "DateCreated": "datetime64[ns]"
    }
  }
}